lsst/__init__.py
lsst/utils/__init__.py
lsst/utils/_packaging.py
lsst/utils/argparsing.py
lsst/utils/classes.py
lsst/utils/db_auth.py
lsst/utils/deprecated.py
lsst/utils/doImport.py
lsst/utils/inheritDoc.py
lsst/utils/introspection.py
lsst/utils/iteration.py
lsst/utils/logging.py
lsst/utils/packages.py
lsst/utils/py.typed
lsst/utils/tests.py
lsst/utils/threads.py
lsst/utils/timer.py
lsst/utils/usage.py
lsst/utils/version.py
lsst/utils/wrappers.py
lsst/utils/plotting/__init__.py
lsst/utils/plotting/figures.py
lsst/utils/plotting/limits.py
lsst/utils/plotting/publication_plots.py
lsst/utils/plotting/rubin.mplstyle
lsst_utils-30.2026.400.dist-info/licenses/COPYRIGHT
lsst_utils-30.2026.400.dist-info/licenses/LICENSE
lsst_utils-30.2026.400.dist-info/METADATA
lsst_utils-30.2026.400.dist-info/WHEEL
lsst_utils-30.2026.400.dist-info/top_level.txt
lsst_utils-30.2026.400.dist-info/zip-safe
lsst_utils-30.2026.400.dist-info/RECORD
