Metadata-Version: 2.4
Name: lsst-utils
Version: 30.2026.400
Summary: Utility functions from Rubin Observatory Data Management for the Legacy Survey of Space and Time (LSST).
Author-email: Rubin Observatory Data Management <dm-admin@lists.lsst.org>
License-Expression: BSD-3-Clause
Project-URL: Homepage, https://github.com/lsst/utils
Project-URL: Source, https://github.com/lsst/utils
Keywords: lsst
Classifier: Intended Audience :: Developers
Classifier: Operating System :: OS Independent
Classifier: Programming Language :: Python :: 3
Classifier: Programming Language :: Python :: 3.10
Classifier: Programming Language :: Python :: 3.11
Classifier: Programming Language :: Python :: 3.12
Classifier: Programming Language :: Python :: 3.13
Classifier: Programming Language :: Python :: 3.14
Requires-Python: >=3.10.0
License-File: COPYRIGHT
License-File: LICENSE
Requires-Dist: numpy>=1.17
Requires-Dist: psutil>=5.7
Requires-Dist: deprecated>=1.2
Requires-Dist: pyyaml>=5.1
Requires-Dist: astropy>=5.0
Requires-Dist: structlog
Requires-Dist: threadpoolctl
Provides-Extra: test
Requires-Dist: pytest>=3.2; extra == "test"
Provides-Extra: plotting
Requires-Dist: matplotlib; extra == "plotting"
Requires-Dist: seaborn; extra == "plotting"
Dynamic: license-file
